tesouro_direto_br/.gitignore
tesouro_direto_br/__init__.py
tesouro_direto_br/tabela_iof_investimentos.xlsx
tesouro_direto_br/tesouro_direto_br.py
tesouro_direto_br/version.py
tesouro_direto_br-0.3.4.dist-info/LICENSE.md
tesouro_direto_br-0.3.4.dist-info/METADATA
tesouro_direto_br-0.3.4.dist-info/WHEEL
tesouro_direto_br-0.3.4.dist-info/RECORD
