Metadata-Version: 2.3
Name: tesouro_direto_br
Version: 0.3.4
Summary: Gerenciamento da Carteira de Titulos Publicos Federais com dados do Tesouro Direto
Author: Rafael Rodrigues
Author-email: rafael.rafarod@gmail.com
Requires-Python: >=3.8.5,<4.0.0
Classifier: Programming Language :: Python :: 3
Classifier: Programming Language :: Python :: 3.9
Classifier: Programming Language :: Python :: 3.10
Classifier: Programming Language :: Python :: 3.11
Classifier: Programming Language :: Python :: 3.12
Classifier: Programming Language :: Python :: 3.13
Requires-Dist: comparar_fundos_br (<=0.1.1) ; python_full_version <= "3.9.0"
Requires-Dist: comparar_fundos_br (>=0.1.2) ; python_version >= "3.10"
Requires-Dist: matplotlib (<=3.7.1) ; python_full_version <= "3.9.0"
Requires-Dist: matplotlib (>=3.10.0) ; python_version >= "3.10"
Requires-Dist: numpy (>=1.24.4,<1.26.0) ; python_full_version <= "3.9.0"
Requires-Dist: numpy (>=1.26.0) ; python_version >= "3.10"
Requires-Dist: pandas (>=1.3.0,<=1.5.3) ; python_full_version <= "3.9.0"
Requires-Dist: pandas (>=2.1.0) ; python_version >= "3.10"
Requires-Dist: pyettj (<=0.3.2) ; python_full_version <= "3.9.0"
Requires-Dist: pyettj (>=0.3.3) ; python_version >= "3.10"
Requires-Dist: requests (>=2.31,<3.0)
Requires-Dist: scipy (>=1.11.0) ; python_version >= "3.10"
Requires-Dist: scipy (>=1.5.1,<=1.10.1) ; python_full_version <= "3.9.0"
